MANIFEST.in
README.txt
setup.py
lowEBMs/__init__.py
lowEBMs.egg-info/PKG-INFO
lowEBMs.egg-info/SOURCES.txt
lowEBMs.egg-info/dependency_links.txt
lowEBMs.egg-info/not-zip-safe
lowEBMs.egg-info/requires.txt
lowEBMs.egg-info/top_level.txt
lowEBMs/Config/FunctionConfigList
lowEBMs/Config/Parameters/SellersParameterization.ini
lowEBMs/ForcingGenerator/VolcanicForcingGenerator.py
lowEBMs/ForcingGenerator/VolcanicForcingGenerator1D.py
lowEBMs/ForcingGenerator/__init__.py
lowEBMs/Forcings/Orbital/pmip3_lm_orbital_parameters.txt
lowEBMs/Forcings/TSI/tsi_DB_lin_40_11yr.txt
lowEBMs/Forcings/TSI/tsi_MEA_11yr.txt
lowEBMs/Forcings/TSI/tsi_SBF_11yr.txt
lowEBMs/Forcings/TSI/tsi_VK.txt
lowEBMs/Forcings/TSI/tsi_WLS.txt
lowEBMs/Forcings/Volcanic/Crowley_800_2050.csv
lowEBMs/Forcings/Volcanic/EVA_2000_3000.txt
lowEBMs/Forcings/Volcanic/EVA_800_2000.txt
lowEBMs/Forcings/Volcanic/Sigl2015.csv
lowEBMs/Packages/Configuration.py
lowEBMs/Packages/Constants.py
lowEBMs/Packages/Functions.py
lowEBMs/Packages/ModelEquation.py
lowEBMs/Packages/Optimization.py
lowEBMs/Packages/RK4.py
lowEBMs/Packages/Variables.py
lowEBMs/Packages/__init__.py
lowEBMs/Tutorials/EBM0D_CO2.py
lowEBMs/Tutorials/EBM0D_simple.py
lowEBMs/Tutorials/EBM0D_volcanic.py
lowEBMs/Tutorials/EBM1D_Budyko_static.py
lowEBMs/Tutorials/EBM1D_Sellers_dynamic.py
lowEBMs/Tutorials/__init__.py
lowEBMs/Tutorials/Config/Demonstration_config_0D_Spinup.ini
lowEBMs/Tutorials/Config/Demonstration_config_1D.ini
lowEBMs/Tutorials/Config/Demonstration_config_Crowley_0D.ini
lowEBMs/Tutorials/Config/Demonstration_config_EVA_0D.ini
lowEBMs/Tutorials/Config/EBM0D_CO2_config.ini
lowEBMs/Tutorials/Config/EBM0D_simple_config.ini
lowEBMs/Tutorials/Config/EBM0D_volcanic_config.ini
lowEBMs/Tutorials/Config/EBM1D_Budyko_dynamic_config.ini
lowEBMs/Tutorials/Config/EBM1D_Budyko_static_config.ini
lowEBMs/Tutorials/Config/EBM1D_OrbitalForcing.ini
lowEBMs/Tutorials/Config/EBM1D_Sellers_dynamic_config.ini
lowEBMs/Tutorials/Config/EBM1D_SolarForcing.ini
lowEBMs/Tutorials/Config/EBM1D_Spinup.ini
lowEBMs/Tutorials/Config/EBM1D_VolcanicForcing.ini
lowEBMs/Tutorials/Config/EBM1D_parallel_Ensemble_config.ini
