Metadata-Version: 2.1
Name: lowEBMs
Version: 1.0.2
Summary: A python implementation of low-dimensional EBMs
Home-page: https://github.com/BenniSchmiedel/Low-dimensional-EBMs
Author: Benjamin Schmiedel
License: MIT
Platform: UNKNOWN
Classifier: Development Status :: 3 - Alpha
